{"vivek_bindra": "Education", "officesonusharma": "Education", "beerbiceps": "Education", "financewithsharan": "Education", "ankurwarikoo": "Education", "prafullmbachaiwala": "Education", "rajshamani": "Education", "dhruvrathee": "Education", "dhattarwalaman": "Education", "drishtiias": "Education", "priyankachopra": "Actor & Movies", "shraddhakapoor": "Actor & Movies", "nehakakkar": "Actor & Movies", "aliaabhatt": "Actor & Movies", "deepikapadukone": "Actor & Movies", "katrinakaif": "Actor & Movies", "jacquelinef143": "Actor & Movies", "akshaykumar": "Actor & Movies", "anushkasharma": "Actor & Movies", "urvashirautela": "Actor & Movies", "aishasharma25": "Healthcare", "swaamiramdev": "Healthcare", "coachsapna": "Healthcare", "bhagyashree.online": "Healthcare", "srisriravishankar": "Healthcare", "iamtarungill": "Healthcare", "leezamangaldas": "Healthcare", "rashmiraifitness": "Healthcare", "simrun.chopra": "Healthcare", "fitnessbyneha": "Healthcare", "virat.kohli": "Sports", "mahi7781": "Sports", "rohitsharma45": "Sports", "ardikpandya93": "Sports", "sureshraina3": "Sports", "yuvisofficial": "Sports", "rahulkl": "Sports", "shikhardofficial": "Sports", "mirzasaniar": "Sports", "yuzi_chahal23": "Sports", "carryminati": "Gaming", "ig_mortal": "Gaming", "triggeredinsaan": "Gaming", "scoutop": "Gaming", "sahilrana": "Gaming", "dynamo__gaming": "Gaming", "ig_jonathangaming": "Gaming", "gyangaming": "Gaming", "therawknee": "Gaming", "snaxgaming": "Gaming"}